kaychen/__init__.py
kaychen/api.py
kaychen/middleware.py
kaychen/orm.py
kaychen/response.py
kaychen-0.1.3.dist-info/METADATA
kaychen-0.1.3.dist-info/WHEEL
kaychen-0.1.3.dist-info/top_level.txt
kaychen-0.1.3.dist-info/RECORD
